{
	"info": {
		"_postman_id": "d77ded84-dd25-42c7-986d-93f4cb3ad552",
		"name": "solution3-delete",
		"schema": "https://schema.getpostman.com/json/collection/v2.1.0/collection.json"
	},
	"item": [
		{
			"name": "bigip5-Test AS3 is running",
			"event": [
				{
					"listen": "test",
					"script": {
						"id": "fd475e8b-be34-422f-ae77-2bdb372badeb",
						"exec": [
							"pm.test(\"AS3 is Running\", function () {",
							"    pm.response.to.have.status(200);",
							"});",
							"",
							""
						],
						"type": "text/javascript"
					}
				},
				{
					"listen": "prerequest",
					"script": {
						"id": "1fb6244a-e827-442d-b6ac-7a0074219c5f",
						"exec": [
							"pm.collectionVariables.set(\"DNS1_NAME\", \"solution3.acme.com\");",
							"pm.collectionVariables.set(\"VS1_NAME\", \"solution3\");",
							"pm.collectionVariables.set(\"PATH_NAME\", \"solution3\");",
							"pm.collectionVariables.set(\"PARTITION_NAME\", \"solution3\");",
							"pm.collectionVariables.set(\"CUSTOM_TYPE\", \"modern\");",
							"",
							"var COUNTER = pm.collectionVariables.get(\"COUNTER\");",
							"",
							"if (COUNTER === \"2\") {",
							"pm.collectionVariables.set(\"BIGIP_MGMT\", \"10.1.1.5\");",
							"pm.collectionVariables.set(\"BIGIP_NUMBER\", \"2\");",
							"pm.collectionVariables.set(\"BIGIP_SCOPE\", pm.environment.get(\"BIGIP2_SCOPE\"));",
							"} else {",
							"pm.collectionVariables.set(\"BIGIP_MGMT\", \"10.1.1.4\");",
							"pm.collectionVariables.set(\"BIGIP_NUMBER\", \"1\");",
							"pm.collectionVariables.set(\"BIGIP_SCOPE\", pm.environment.get(\"BIGIP1_SCOPE\"));",
							"pm.collectionVariables.set('COUNTER',\"1\" );",
							"",
							"}"
						],
						"type": "text/javascript"
					}
				}
			],
			"request": {
				"auth": {
					"type": "basic",
					"basic": [
						{
							"key": "password",
							"value": "admin",
							"type": "string"
						},
						{
							"key": "username",
							"value": "admin",
							"type": "string"
						}
					]
				},
				"method": "GET",
				"header": [],
				"url": {
					"raw": "https://10.1.1.11/mgmt/shared/appsvcs/info",
					"protocol": "https",
					"host": [
						"10",
						"1",
						"1",
						"11"
					],
					"path": [
						"mgmt",
						"shared",
						"appsvcs",
						"info"
					]
				}
			},
			"response": []
		},
		{
			"name": "bigip5-Delete WideIP1",
			"event": [
				{
					"listen": "prerequest",
					"script": {
						"id": "e37841d4-cab8-4749-b2f2-df0b2f1311c8",
						"exec": [
							""
						],
						"type": "text/javascript"
					}
				},
				{
					"listen": "test",
					"script": {
						"id": "fac1d049-74df-4657-b737-6f1991df4655",
						"exec": [
							"",
							"if (responseCode.code === 200) {",
							"pm.test(\"Wide IP deleted\", function () {",
							"    pm.response.to.have.status(200);",
							"});",
							"} else if (responseCode.code === 422) {",
							"pm.test(\"WideIP does not exist\", function () {",
							"    pm.expect(pm.response.text()).to.include(\"path does not exist\");",
							"});",
							"",
							"}"
						],
						"type": "text/javascript"
					}
				}
			],
			"request": {
				"auth": {
					"type": "basic",
					"basic": [
						{
							"key": "password",
							"value": "admin",
							"type": "string"
						},
						{
							"key": "username",
							"value": "admin",
							"type": "string"
						}
					]
				},
				"method": "PATCH",
				"header": [],
				"body": {
					"mode": "raw",
					"raw": "[\n{\n\t\"op\":\"remove\",\n\t\"path\":\"{{PARTITION_NAME}}/Application\"\n \n}\n]"
				},
				"url": {
					"raw": "https://10.1.1.11/mgmt/shared/appsvcs/declare",
					"protocol": "https",
					"host": [
						"10",
						"1",
						"1",
						"11"
					],
					"path": [
						"mgmt",
						"shared",
						"appsvcs",
						"declare"
					]
				}
			},
			"response": []
		},
		{
			"name": "bigip5-Get bigip Server VS1 address",
			"event": [
				{
					"listen": "prerequest",
					"script": {
						"id": "2f5c205a-4f37-4087-afa3-20297d427b42",
						"exec": [
							"setTimeout(function(){}, 1000);"
						],
						"type": "text/javascript"
					}
				},
				{
					"listen": "test",
					"script": {
						"id": "c1445954-a841-4a44-8809-36ad1c3f57b2",
						"exec": [
							"if (responseCode.code === 200) {",
							"",
							"    pm.test(\"VS Address found\", function () {",
							"        pm.response.to.have.status(200);",
							"",
							"        var jsonData = JSON.parse(responseBody);",
							"        pm.collectionVariables.set(\"DNS_DEST\", jsonData.destination);",
							"        address = (pm.collectionVariables.get(\"DNS_DEST\")).split(\":\");",
							"        pm.collectionVariables.set('BIGIP_ADDRESS1', address[0]);",
							"    });",
							"} else",
							"    pm.test(\"VS does not exist\", function () {",
							"        pm.response.to.have.status(404);",
							"    });",
							"",
							"",
							"",
							"",
							"",
							"",
							"",
							"",
							"",
							"",
							""
						],
						"type": "text/javascript"
					}
				}
			],
			"protocolProfileBehavior": {
				"disableBodyPruning": true
			},
			"request": {
				"auth": {
					"type": "basic",
					"basic": [
						{
							"key": "password",
							"value": "admin",
							"type": "string"
						},
						{
							"key": "username",
							"value": "admin",
							"type": "string"
						}
					]
				},
				"method": "GET",
				"header": [
					{
						"key": "Content-Type",
						"type": "text",
						"value": "application/json"
					}
				],
				"body": {
					"mode": "raw",
					"raw": ""
				},
				"url": {
					"raw": "https://10.1.1.11/mgmt/tm/gtm/server/~Common~bigip{{BIGIP_NUMBER}}.f5lab.local/virtual-servers/~{{PARTITION_NAME}}~{{PATH_NAME}}~{{VS1_NAME}}",
					"protocol": "https",
					"host": [
						"10",
						"1",
						"1",
						"11"
					],
					"path": [
						"mgmt",
						"tm",
						"gtm",
						"server",
						"~Common~bigip{{BIGIP_NUMBER}}.f5lab.local",
						"virtual-servers",
						"~{{PARTITION_NAME}}~{{PATH_NAME}}~{{VS1_NAME}}"
					]
				}
			},
			"response": []
		},
		{
			"name": "bigip-Checkin Address",
			"event": [
				{
					"listen": "test",
					"script": {
						"id": "63096f81-b9f0-400d-9580-d3f368b5beda",
						"exec": [
							"var jsonData = pm.response.json();",
							"",
							"",
							"",
							"  if(jsonData.status === \"Success\") {",
							"pm.test(\"Address returned to Scope\", function () {",
							"    pm.response.to.have.status(200);",
							"",
							"});",
							"} else {",
							"",
							"pm.test(\"Address not assigned in Scope\", function () {",
							"    pm.response.to.have.status(200);",
							"});",
							"}",
							""
						],
						"type": "text/javascript"
					}
				}
			],
			"request": {
				"method": "DELETE",
				"header": [],
				"body": {
					"mode": "raw",
					"raw": ""
				},
				"url": {
					"raw": "http://10.1.20.6:81/addr/checkin?address={{BIGIP_ADDRESS1}}",
					"protocol": "http",
					"host": [
						"10",
						"1",
						"20",
						"6"
					],
					"port": "81",
					"path": [
						"addr",
						"checkin"
					],
					"query": [
						{
							"key": "address",
							"value": "{{BIGIP_ADDRESS1}}"
						}
					]
				}
			},
			"response": []
		},
		{
			"name": "bigip5-Delete bigip1 Server VS",
			"event": [
				{
					"listen": "prerequest",
					"script": {
						"id": "6a9f094e-c2b5-4c5c-ac6c-26265107a753",
						"exec": [
							"setTimeout(function(){}, 1000);"
						],
						"type": "text/javascript"
					}
				},
				{
					"listen": "test",
					"script": {
						"id": "170bbe0d-a05e-4bba-b950-e8c1d8860dc1",
						"exec": [
							"if (responseCode.code === 200) {",
							"pm.test(\"VS deleted from server\", function () {",
							"    pm.response.to.have.status(200);",
							"});",
							"} else ",
							"pm.test(\"VS does not exist\", function () {",
							"    pm.response.to.have.status(404);",
							"});",
							"",
							"",
							""
						],
						"type": "text/javascript"
					}
				}
			],
			"request": {
				"auth": {
					"type": "basic",
					"basic": [
						{
							"key": "password",
							"value": "admin",
							"type": "string"
						},
						{
							"key": "username",
							"value": "admin",
							"type": "string"
						}
					]
				},
				"method": "DELETE",
				"header": [
					{
						"key": "Content-Type",
						"type": "text",
						"value": "application/json"
					}
				],
				"body": {
					"mode": "raw",
					"raw": ""
				},
				"url": {
					"raw": "https://10.1.1.11/mgmt/tm/gtm/server/~Common~bigip{{BIGIP_NUMBER}}.f5lab.local/virtual-servers/~{{PARTITION_NAME}}~{{PATH_NAME}}~{{VS1_NAME}}",
					"protocol": "https",
					"host": [
						"10",
						"1",
						"1",
						"11"
					],
					"path": [
						"mgmt",
						"tm",
						"gtm",
						"server",
						"~Common~bigip{{BIGIP_NUMBER}}.f5lab.local",
						"virtual-servers",
						"~{{PARTITION_NAME}}~{{PATH_NAME}}~{{VS1_NAME}}"
					]
				}
			},
			"response": []
		},
		{
			"name": "bigip-Test AS3 is running",
			"event": [
				{
					"listen": "test",
					"script": {
						"id": "eb6bb3d7-47d0-432c-b5eb-a4c62d62f20e",
						"exec": [
							"",
							"pm.test(\"AS3 is Running\", function () {",
							"    pm.response.to.have.status(200);",
							"});",
							"",
							""
						],
						"type": "text/javascript"
					}
				}
			],
			"request": {
				"auth": {
					"type": "basic",
					"basic": [
						{
							"key": "password",
							"value": "admin",
							"type": "string"
						},
						{
							"key": "username",
							"value": "admin",
							"type": "string"
						}
					]
				},
				"method": "GET",
				"header": [],
				"url": {
					"raw": "https://{{BIGIP_MGMT}}/mgmt/shared/appsvcs/info",
					"protocol": "https",
					"host": [
						"{{BIGIP_MGMT}}"
					],
					"path": [
						"mgmt",
						"shared",
						"appsvcs",
						"info"
					]
				}
			},
			"response": []
		},
		{
			"name": "bigip-delete Application",
			"event": [
				{
					"listen": "prerequest",
					"script": {
						"id": "67cb0137-8b0e-48ca-b753-1d174bbfed9a",
						"exec": [
							""
						],
						"type": "text/javascript"
					}
				},
				{
					"listen": "test",
					"script": {
						"id": "adb732da-0845-4586-b16c-7e496c39728f",
						"exec": [
							"",
							"",
							"pm.test(\"Application deleted\", function () {",
							"    pm.response.to.have.status(200);",
							"});",
							"",
							"",
							""
						],
						"type": "text/javascript"
					}
				}
			],
			"request": {
				"auth": {
					"type": "basic",
					"basic": [
						{
							"key": "password",
							"value": "admin",
							"type": "string"
						},
						{
							"key": "username",
							"value": "admin",
							"type": "string"
						}
					]
				},
				"method": "DELETE",
				"header": [],
				"body": {
					"mode": "raw",
					"raw": ""
				},
				"url": {
					"raw": "https://{{BIGIP_MGMT}}/mgmt/shared/appsvcs/declare/{{PARTITION_NAME}}",
					"protocol": "https",
					"host": [
						"{{BIGIP_MGMT}}"
					],
					"path": [
						"mgmt",
						"shared",
						"appsvcs",
						"declare",
						"{{PARTITION_NAME}}"
					]
				}
			},
			"response": []
		},
		{
			"name": "bigip-Delete Node",
			"event": [
				{
					"listen": "prerequest",
					"script": {
						"id": "ab1c2a60-5fbd-4ecd-9ad3-092b8a828931",
						"exec": [
							"setTimeout(function(){}, 1000);"
						],
						"type": "text/javascript"
					}
				},
				{
					"listen": "test",
					"script": {
						"id": "1e1b2df9-c512-4d4c-94ee-b006b7bba3ef",
						"exec": [
							"if (responseCode.code === 200) {",
							"",
							"pm.test(\"Node deleted\", function () {",
							"    pm.response.to.have.status(200);",
							"});",
							"} else if (responseCode.code === 404) { ",
							"pm.test(\"Node does not exist\", function () {",
							"    pm.response.to.have.status(404);",
							"});",
							"} else if (responseCode.code === 400) {",
							"pm.test(\"Unable to Delete Node. Still in use\", function () {",
							"    pm.expect(pm.response.text()).to.include(\"member of pool\");",
							"});",
							"",
							"}"
						],
						"type": "text/javascript"
					}
				}
			],
			"request": {
				"auth": {
					"type": "basic",
					"basic": [
						{
							"key": "password",
							"value": "admin",
							"type": "string"
						},
						{
							"key": "username",
							"value": "admin",
							"type": "string"
						}
					]
				},
				"method": "DELETE",
				"header": [
					{
						"key": "Content-Type",
						"type": "text",
						"value": "application/json"
					}
				],
				"body": {
					"mode": "raw",
					"raw": ""
				},
				"url": {
					"raw": "https://{{BIGIP_MGMT}}/mgmt/tm/ltm/node/10.1.20.6",
					"protocol": "https",
					"host": [
						"{{BIGIP_MGMT}}"
					],
					"path": [
						"mgmt",
						"tm",
						"ltm",
						"node",
						"10.1.20.6"
					]
				}
			},
			"response": []
		},
		{
			"name": "bigip-delete-profile",
			"event": [
				{
					"listen": "test",
					"script": {
						"id": "61a98fdb-caa2-4856-84cd-4bd0351dd89e",
						"exec": [
							"if (responseCode.code === 200) {\r",
							"pm.test(\"Profile Deleted\", function () {\r",
							"    pm.response.to.have.status(200);\r",
							"});\r",
							"} else \r",
							"pm.test(\"Profile Does Not Exist\", function () {\r",
							"    pm.response.to.have.status(404);\r",
							"});\r",
							"\r",
							"\r",
							"setTimeout(function(){}, 3000);"
						],
						"type": "text/javascript"
					}
				},
				{
					"listen": "prerequest",
					"script": {
						"id": "e773cb74-7556-43b3-9675-88309d446946",
						"exec": [
							""
						],
						"type": "text/javascript"
					}
				}
			],
			"request": {
				"auth": {
					"type": "basic",
					"basic": [
						{
							"key": "password",
							"value": "admin",
							"type": "string"
						},
						{
							"key": "username",
							"value": "admin",
							"type": "string"
						}
					]
				},
				"method": "DELETE",
				"header": [
					{
						"key": "Content-Type",
						"type": "text",
						"value": "application/json"
					},
					{
						"key": "X-F5-REST-Coordination-Id",
						"type": "text",
						"value": "",
						"disabled": true
					}
				],
				"body": {
					"mode": "raw",
					"raw": ""
				},
				"url": {
					"raw": "https://{{BIGIP_MGMT}}//mgmt/tm/apm/profile/access/~Common~{{PARTITION_NAME}}-psp",
					"protocol": "https",
					"host": [
						"{{BIGIP_MGMT}}"
					],
					"path": [
						"",
						"mgmt",
						"tm",
						"apm",
						"profile",
						"access",
						"~Common~{{PARTITION_NAME}}-psp"
					]
				}
			},
			"response": []
		},
		{
			"name": "bigip-delete-Policy",
			"event": [
				{
					"listen": "test",
					"script": {
						"id": "835c9b25-3d5b-4b9c-830e-c6ef3a135cb9",
						"exec": [
							"if (responseCode.code === 200) {\r",
							"pm.test(\"Policy Deleted\", function () {\r",
							"    pm.response.to.have.status(200);\r",
							"});\r",
							"} else \r",
							"pm.test(\"Policy Does Not Exist\", function () {\r",
							"    pm.response.to.have.status(404);\r",
							"});\r",
							""
						],
						"type": "text/javascript"
					}
				},
				{
					"listen": "prerequest",
					"script": {
						"id": "6d52bab4-a9f7-432c-b0df-40bba7012207",
						"exec": [
							""
						],
						"type": "text/javascript"
					}
				}
			],
			"request": {
				"auth": {
					"type": "basic",
					"basic": [
						{
							"key": "password",
							"value": "admin",
							"type": "string"
						},
						{
							"key": "username",
							"value": "admin",
							"type": "string"
						}
					]
				},
				"method": "DELETE",
				"header": [
					{
						"key": "Content-Type",
						"type": "text",
						"value": "application/json"
					},
					{
						"key": "X-F5-REST-Coordination-Id",
						"type": "text",
						"value": "{{TRANSID}}",
						"disabled": true
					}
				],
				"body": {
					"mode": "raw",
					"raw": ""
				},
				"url": {
					"raw": "https://{{BIGIP_MGMT}}/mgmt/tm/apm/policy/access-policy/~Common~{{PARTITION_NAME}}-psp",
					"protocol": "https",
					"host": [
						"{{BIGIP_MGMT}}"
					],
					"path": [
						"mgmt",
						"tm",
						"apm",
						"policy",
						"access-policy",
						"~Common~{{PARTITION_NAME}}-psp"
					]
				}
			},
			"response": []
		},
		{
			"name": "bigip-delete-sp",
			"event": [
				{
					"listen": "test",
					"script": {
						"id": "1d105b22-cdc1-46e1-b280-1092122d8907",
						"exec": [
							"if (responseCode.code === 200) {",
							"",
							"pm.test(\"SP Deleted\", function () {",
							"    pm.response.to.have.status(200);",
							"});",
							"} else ",
							"pm.test(\"SPn Does Not Exist\", function () {",
							"    pm.response.to.have.status(404);",
							"});",
							"",
							""
						],
						"type": "text/javascript"
					}
				},
				{
					"listen": "prerequest",
					"script": {
						"id": "3efb1d9e-b08c-437c-81e3-a447c4d90bfb",
						"exec": [
							""
						],
						"type": "text/javascript"
					}
				}
			],
			"request": {
				"auth": {
					"type": "basic",
					"basic": [
						{
							"key": "password",
							"value": "admin",
							"type": "string"
						},
						{
							"key": "username",
							"value": "admin",
							"type": "string"
						}
					]
				},
				"method": "DELETE",
				"header": [
					{
						"key": "Content-Type",
						"type": "text",
						"value": "application/json"
					},
					{
						"key": "X-F5-REST-Coordination-Id",
						"type": "text",
						"value": "{{TRANSID}}",
						"disabled": true
					}
				],
				"body": {
					"mode": "raw",
					"raw": ""
				},
				"url": {
					"raw": "https://{{BIGIP_MGMT}}/mgmt/tm/apm/aaa/saml/~Common~{{VS1_NAME}}-SP",
					"protocol": "https",
					"host": [
						"{{BIGIP_MGMT}}"
					],
					"path": [
						"mgmt",
						"tm",
						"apm",
						"aaa",
						"saml",
						"~Common~{{VS1_NAME}}-SP"
					]
				}
			},
			"response": []
		},
		{
			"name": "bigip-delete-idp",
			"event": [
				{
					"listen": "test",
					"script": {
						"id": "f2628c5c-e4cb-41de-b991-ce51cd8f5dd7",
						"exec": [
							"if (responseCode.code === 200) {",
							"pm.test(\"IDP Deleted\", function () {",
							"    pm.response.to.have.status(200);",
							"});",
							"} else ",
							"pm.test(\"IDP Does Not Exist\", function () {",
							"    pm.response.to.have.status(404);",
							"});",
							"",
							""
						],
						"type": "text/javascript"
					}
				},
				{
					"listen": "prerequest",
					"script": {
						"id": "799e2f95-610d-410e-b5bf-d1b6c5b402ba",
						"exec": [
							""
						],
						"type": "text/javascript"
					}
				}
			],
			"request": {
				"auth": {
					"type": "basic",
					"basic": [
						{
							"key": "password",
							"value": "admin",
							"type": "string"
						},
						{
							"key": "username",
							"value": "admin",
							"type": "string"
						}
					]
				},
				"method": "DELETE",
				"header": [
					{
						"key": "Content-Type",
						"type": "text",
						"value": "application/json"
					},
					{
						"key": "X-F5-REST-Coordination-Id",
						"type": "text",
						"value": "{{TRANSID}}",
						"disabled": true
					}
				],
				"body": {
					"mode": "raw",
					"raw": ""
				},
				"url": {
					"raw": "https://{{BIGIP_MGMT}}/mgmt/tm/apm/aaa/saml-idp-connector/~Common~{{VS1_NAME}}-IDP",
					"protocol": "https",
					"host": [
						"{{BIGIP_MGMT}}"
					],
					"path": [
						"mgmt",
						"tm",
						"apm",
						"aaa",
						"saml-idp-connector",
						"~Common~{{VS1_NAME}}-IDP"
					]
				}
			},
			"response": []
		},
		{
			"name": "bigip-delete-okta cert",
			"event": [
				{
					"listen": "test",
					"script": {
						"id": "c818d3f8-beb2-47a8-842f-fb1a853f4ea8",
						"exec": [
							"\r",
							"\r",
							"var DC2_APM = pm.environment.get(\"DC2_APM\");\r",
							"var COUNTER = pm.collectionVariables.get(\"COUNTER\");\r",
							"\r",
							"if (DC2_APM === \"true\" && COUNTER === \"1\") {\r",
							"postman.setNextRequest(\"bigip5-Test AS3 is running\");\r",
							"pm.collectionVariables.set(\"COUNTER\", \"2\" );\r",
							"\r",
							"} else {\r",
							"\r",
							"\r",
							"}"
						],
						"type": "text/javascript"
					}
				}
			],
			"request": {
				"auth": {
					"type": "basic",
					"basic": [
						{
							"key": "password",
							"value": "admin",
							"type": "string"
						},
						{
							"key": "username",
							"value": "admin",
							"type": "string"
						}
					]
				},
				"method": "DELETE",
				"header": [
					{
						"key": "Content-Type",
						"type": "text",
						"value": "application/json"
					},
					{
						"key": "X-F5-REST-Coordination-Id",
						"type": "text",
						"value": "",
						"disabled": true
					},
					{
						"key": "Content-Range",
						"type": "text",
						"value": "0-1321/1322",
						"disabled": true
					}
				],
				"body": {
					"mode": "raw",
					"raw": ""
				},
				"url": {
					"raw": "https://{{BIGIP_MGMT}}/mgmt/tm/sys/crypto/cert/~Common~{{VS1_NAME}}",
					"protocol": "https",
					"host": [
						"{{BIGIP_MGMT}}"
					],
					"path": [
						"mgmt",
						"tm",
						"sys",
						"crypto",
						"cert",
						"~Common~{{VS1_NAME}}"
					]
				}
			},
			"response": []
		},
		{
			"name": "iis-delete website",
			"event": [
				{
					"listen": "test",
					"script": {
						"id": "7ce9fd27-8f4b-4142-9a2b-479ce4cd1867",
						"exec": [
							"",
							"",
							"var jsonData = pm.response.json();",
							"pm.test(\"Website Deleted\", function () {",
							"",
							"    pm.expect(jsonData.status).to.eql(\"Success\");",
							"});",
							"",
							"pm.collectionVariables.set(\"COUNTER\", \"1\" );",
							""
						],
						"type": "text/javascript"
					}
				}
			],
			"request": {
				"method": "DELETE",
				"header": [],
				"body": {
					"mode": "raw",
					"raw": "{\n\"site_name\":\"{{DNS1_NAME}}\" \n}"
				},
				"url": {
					"raw": "http://10.1.20.6:81/website",
					"protocol": "http",
					"host": [
						"10",
						"1",
						"20",
						"6"
					],
					"port": "81",
					"path": [
						"website"
					]
				}
			},
			"response": []
		}
	],
	"event": [
		{
			"listen": "prerequest",
			"script": {
				"id": "4beaf881-9083-4e7d-b4cc-38d510a29f3e",
				"type": "text/javascript",
				"exec": [
					""
				]
			}
		},
		{
			"listen": "test",
			"script": {
				"id": "c7ac82b8-df7a-4786-8ca3-eff242af24ac",
				"type": "text/javascript",
				"exec": [
					""
				]
			}
		}
	],
	"variable": [
		{
			"id": "58899a2f-d5d2-4b73-b9bb-38205899fb1b",
			"key": "BIGIP_MGMT",
			"value": ""
		},
		{
			"id": "95709a38-1b15-4d23-a0ca-a4bc05c65b5c",
			"key": "BIGIP_NUMBER",
			"value": ""
		},
		{
			"id": "cf7f80b4-0cee-4265-a599-165566997ed0",
			"key": "BIGIP_SCOPE",
			"value": ""
		},
		{
			"id": "bb4d5d07-485d-4322-a10b-9b05dd1a8674",
			"key": "COUNTER",
			"value": ""
		},
		{
			"id": "b60d532e-5736-4466-908f-d91ec699cb75",
			"key": "CUSTOM_TYPE",
			"value": ""
		},
		{
			"id": "393a43fb-dd20-4510-8f1a-ede9d99f9e93",
			"key": "DNS1_NAME",
			"value": ""
		},
		{
			"id": "1d10f167-5225-434e-8a87-db0d7e792309",
			"key": "DNS2_NAME",
			"value": ""
		},
		{
			"id": "f2a421a4-f7ad-42df-8c19-860396323218",
			"key": "PARTITION_NAME",
			"value": ""
		},
		{
			"id": "0ca0c9c5-eb5e-4800-9b30-1d901d2595fd",
			"key": "PATH_NAME",
			"value": ""
		},
		{
			"id": "9a0e6d23-8045-4cd7-adf4-527d08fb493f",
			"key": "VS1_NAME",
			"value": ""
		},
		{
			"id": "d51c2c43-f480-4b02-9845-e9b06a9d09b2",
			"key": "PRIOR_RESPONSE",
			"value": ""
		},
		{
			"id": "74c199f8-aa0c-4e75-a427-4daa92082246",
			"key": "BIGIP_ADDRESS1",
			"value": ""
		},
		{
			"id": "9b9b81fe-a62e-4486-80ad-4897ebda800c",
			"key": "DNS_DEST",
			"value": ""
		}
	],
	"protocolProfileBehavior": {}
}